tokenizer/__init__.py
tokenizer/tokenization_small100.py
mm_tokenizer-0.4.0.dist-info/METADATA
mm_tokenizer-0.4.0.dist-info/WHEEL
mm_tokenizer-0.4.0.dist-info/RECORD
